{
  "type": "minecraft:crafting_shaped",
  "category": "equipment",
  "pattern": [
    "111",
    "121",
    "111"
  ],
  "key": {
    "1": "minecraft:copper_block",
    "2": "minecraft:iron_pickaxe"
  },
  "result": {
    "id": "minecraft:iron_pickaxe",
    "count": 1,
    "components": {
      "minecraft:tool": {
        "rules": [
          {
            "blocks": "#minecraft:incorrect_for_iron_tool",
            "correct_for_drops": false
          },
          {
            "blocks": "#minecraft:mineable/pickaxe",
            "correct_for_drops": true,
            "speed": 10.0
          }
        ]
      },
      "minecraft:lore": [
        "''",
        "{'translate': 'item.modifiers.mainhand', 'color':'gray', 'italic':false}",
        "[' ',{'translate':'attribute.modifier.equals.0','with':['4',{'translate':'attribute.name.attack_damage'}],'color':'dark_green','italic':false}]",
        "[' ',{'translate':'attribute.modifier.equals.0','with':['1.3',{'translate':'attribute.name.attack_speed'}],'color':'dark_green','italic':false}]"
      ],
      "minecraft:max_damage": 1000,
      "minecraft:item_model": "copper_items:copper_pickaxe",
      "minecraft:item_name": "'Reinforced Iron Pickaxe'",
      "minecraft:custom_model_data": {"floats": [43002]}
    }
  }
}